tahoe_figures_plugins/__init__.py
tahoe_figures_plugins/sites.py
tahoe_figures_plugins-0.1.1.dist-info/LICENSE
tahoe_figures_plugins-0.1.1.dist-info/METADATA
tahoe_figures_plugins-0.1.1.dist-info/WHEEL
tahoe_figures_plugins-0.1.1.dist-info/top_level.txt
tahoe_figures_plugins-0.1.1.dist-info/RECORD
