Metadata-Version: 2.1
Name: tahoe-figures-plugins
Version: 0.1.1
Summary: Backends and customizations for Figures in Tahoe.
License-File: LICENSE
